LICENSE
README.md
setup.py
elmovisualizer_APP.egg-info/PKG-INFO
elmovisualizer_APP.egg-info/SOURCES.txt
elmovisualizer_APP.egg-info/dependency_links.txt
elmovisualizer_APP.egg-info/requires.txt
elmovisualizer_APP.egg-info/top_level.txt
visualizer/__init__.py