Metadata-Version: 2.1
Name: elmovisualizer-APP
Version: 1.0.2
Summary: View Elmo Visualizer Camera Utilities
Author: VeeKay Consultancy Services
Author-email: <veekayit@gmail.com>
Keywords: visualizer,elmo
Classifier: Development Status :: 5 - Production/Stable
Classifier: Intended Audience :: Developers
Classifier: Programming Language :: Python :: 3
Classifier: Operating System :: Unix
Classifier: Operating System :: MacOS :: MacOS X
Classifier: Operating System :: Microsoft :: Windows
License-File: LICENSE
